ack_mining/__init__.py
ack_mining/flair_predictor.py
ack_mining/flair_trainer.py
ack_mining/training_data_converter.py
doc2vec/__init__.py
doc2vec/doc2vecModel.py
doc2vec/docSimilarityManager.py
doc2vec/train.py
document_classification/__init__.py
document_classification/lasso_term_extraction.py
document_classification/ml_textclassification.py
document_classification/test_ml_text_classfier.py
document_clustering/__init__.py
document_clustering/documentclustering.py
document_clustering/test_document_clustering.py
examples/__init__.py
examples/doc2vec_tester.py
examples/doc2vec_trainer.py
examples/fasttext_tester.py
examples/fasttext_trainer.py
examples/glove_tester.py
examples/koreanKeywordTest.py
examples/koreanLemmatizationTest.py
examples/koreanNounExtractionTest.py
examples/koreanSegmentationTest.py
examples/koreanSpecialTokenizerTest.py
examples/koreanTokenizerTest.py
examples/naver_newscomments_processor.py
examples/node2vec_tester.py
examples/node2vec_traianer.py
examples/test222.py
examples/test3.py
examples/test4.py
examples/testBertLSTM.py
examples/testCooccurrence.py
examples/testDocTermMatrix.py
examples/testEXCo.py
examples/testFirst.py
examples/testMallet.py
examples/testPMI.py
examples/testSVM.py
examples/test_korean_lemmatizer.py
examples/test_pyTextMinerTopicModel.py
examples/test_word2veclite.py
examples/testt.py
examples/word2vec_tester.py
examples/word2vec_trainer.py
examples/zipfsManager.py
glove-win_devc_x64/__init__.py
glove-win_devc_x64/eval/__init__.py
glove-win_devc_x64/eval/python/__init__.py
glove-win_devc_x64/eval/python/distance.py
glove-win_devc_x64/eval/python/evaluate.py
glove-win_devc_x64/eval/python/word_analogy.py
lda2vec/__init__.py
lda2vec/alias_multinomial.py
lda2vec/get_windows.py
lda2vec/lda2vecManager.py
lda2vec/lda2vec_loss.py
lda2vec/lda2vec_model.py
lda2vec/load_20newsgroups.py
lda2vec/preprocess.py
lda2vec/run_20newsgroups.py
lda2vec/train.py
lda2vec/training.py
pyTextMiner/__init__.py
pyTextMiner/chunker/__init__.py
pyTextMiner-1.1.116.dist-info/LICENSE
pyTextMiner-1.1.116.dist-info/METADATA
pyTextMiner-1.1.116.dist-info/WHEEL
pyTextMiner-1.1.116.dist-info/top_level.txt
pyTextMiner-1.1.116.dist-info/RECORD
